kube_compose/__init__.py
kube_compose/__main__.py
kube_compose/charts/kube-compose/Chart.yaml
kube_compose/charts/kube-compose/templates/deployment.yaml
kube_compose/cli/__init__.py
kube_compose/cli/config.py
kube_compose/cli/configmap/__init__.py
kube_compose/cli/configmap/create.py
kube_compose/cli/configmap/inspect.py
kube_compose/cli/configmap/ls.py
kube_compose/cli/configmap/rm.py
kube_compose/cli/configmap/template.py
kube_compose/cli/cp.py
kube_compose/cli/diff.py
kube_compose/cli/down.py
kube_compose/cli/drift.py
kube_compose/cli/events.py
kube_compose/cli/exec.py
kube_compose/cli/get/__init__.py
kube_compose/cli/get/all.py
kube_compose/cli/get/manifest.py
kube_compose/cli/get/metadata.py
kube_compose/cli/get/values.py
kube_compose/cli/history.py
kube_compose/cli/init.py
kube_compose/cli/kill.py
kube_compose/cli/logs.py
kube_compose/cli/ls.py
kube_compose/cli/port-forward.py
kube_compose/cli/ps.py
kube_compose/cli/restart.py
kube_compose/cli/rollback.py
kube_compose/cli/run.py
kube_compose/cli/scale.py
kube_compose/cli/start.py
kube_compose/cli/stats.py
kube_compose/cli/status.py
kube_compose/cli/stop.py
kube_compose/cli/template.py
kube_compose/cli/top.py
kube_compose/cli/up.py
kube_compose/cli/version.py
kube_compose/cli/volume/__init__.py
kube_compose/cli/volume/create.py
kube_compose/cli/volume/inspect.py
kube_compose/cli/volume/ls.py
kube_compose/cli/volume/rm.py
kube_compose/cli/volume/template.py
kube_compose/utils.py
kube_compose-0.11.0.dist-info/LICENSE
kube_compose-0.11.0.dist-info/METADATA
kube_compose-0.11.0.dist-info/WHEEL
kube_compose-0.11.0.dist-info/entry_points.txt
kube_compose-0.11.0.dist-info/RECORD
