Metadata-Version: 2.3
Name: kube-compose
Version: 0.11.0
Summary: An opinionated way of deploying docker-compose to kubernetes clusters by managing them with a helm chart.
Author: Daniel J. B. Clarke
Author-email: u8sand@gmail.com
Requires-Python: >=3.10
Classifier: Programming Language :: Python :: 3
Classifier: Programming Language :: Python :: 3.10
Classifier: Programming Language :: Python :: 3.11
Classifier: Programming Language :: Python :: 3.12
Classifier: Programming Language :: Python :: 3.13
Requires-Dist: click (>=8.2.1,<9.0.0)
Requires-Dist: pyyaml (>=6.0.2,<7.0.0)
Requires-Dist: ruamel-yaml (>=0.18.14,<0.19.0)
